py_mdr/__init__.py
py_mdr/client.py
py_mdr/handler.py
py_mdr/helper.py
py_mdr/ocsf_models/__init__.py
py_mdr/ocsf_models/events/__init__.py
py_mdr/ocsf_models/events/base_event.py
py_mdr/ocsf_models/events/application_activity/__init__.py
py_mdr/ocsf_models/events/discovery/__init__.py
py_mdr/ocsf_models/events/discovery/software_inventory.py
py_mdr/ocsf_models/events/findings/__init__.py
py_mdr/ocsf_models/events/findings/detection_finding.py
py_mdr/ocsf_models/events/findings/vulnerability_finding.py
py_mdr/ocsf_models/events/identity_access_mgmt/__init__.py
py_mdr/ocsf_models/events/network_activity/__init__.py
py_mdr/ocsf_models/events/remediation/__init__.py
py_mdr/ocsf_models/events/system_activity/__init__.py
py_mdr/ocsf_models/events/system_activity/event_log_activity.py
py_mdr/ocsf_models/objects/__init__.py
py_mdr/ocsf_models/objects/account.py
py_mdr/ocsf_models/objects/actor.py
py_mdr/ocsf_models/objects/affected_code.py
py_mdr/ocsf_models/objects/agent.py
py_mdr/ocsf_models/objects/analytic.py
py_mdr/ocsf_models/objects/api.py
py_mdr/ocsf_models/objects/autonomous_system.py
py_mdr/ocsf_models/objects/base_model.py
py_mdr/ocsf_models/objects/cloud.py
py_mdr/ocsf_models/objects/container.py
py_mdr/ocsf_models/objects/database.py
py_mdr/ocsf_models/objects/device.py
py_mdr/ocsf_models/objects/device_hardware_info.py
py_mdr/ocsf_models/objects/digital_certificate.py
py_mdr/ocsf_models/objects/digital_signature.py
py_mdr/ocsf_models/objects/dns_query.py
py_mdr/ocsf_models/objects/email.py
py_mdr/ocsf_models/objects/enrichment.py
py_mdr/ocsf_models/objects/evidence_artifacts.py
py_mdr/ocsf_models/objects/file.py
py_mdr/ocsf_models/objects/finding_info.py
py_mdr/ocsf_models/objects/fingerprint.py
py_mdr/ocsf_models/objects/geolocation.py
py_mdr/ocsf_models/objects/group.py
py_mdr/ocsf_models/objects/image.py
py_mdr/ocsf_models/objects/kb_article.py
py_mdr/ocsf_models/objects/kill_chain_phase.py
py_mdr/ocsf_models/objects/ldap_person.py
py_mdr-0.7.2.dist-info/METADATA
py_mdr-0.7.2.dist-info/WHEEL
py_mdr-0.7.2.dist-info/licenses/LICENSE
py_mdr-0.7.2.dist-info/RECORD
