Metadata-Version: 2.4
Name: py-mdr
Version: 0.7.2
Summary: Project to help interacting with the internal MDR project.
Author-email: "Jorge L. Martinez" <jmartinez@schubergphilis.com>
License-File: LICENSE
Requires-Python: >=3.10
Requires-Dist: httpx~=0.28.1
Requires-Dist: requests~=2.32.5
